letterboxd/__init__.py
letterboxd/api.py
letterboxd/config.py
letterboxd/letterboxd.py
letterboxd/user.py
letterboxd/services/__init__.py
letterboxd/services/auth.py
letterboxd/services/film.py
letterboxd/services/list.py
letterboxd/services/member.py
letterboxd/services/search.py
letterboxd-0.3.0.dist-info/METADATA
letterboxd-0.3.0.dist-info/RECORD
letterboxd-0.3.0.dist-info/WHEEL
letterboxd-0.3.0.dist-info/top_level.txt
