Metadata-Version: 2.1
Name: letterboxd
Version: 0.3.0
Summary: Python 3 wrapper for the Letterboxd API
Home-page: https://github.com/bobtiki/letterboxd/
Author: Mark Boszko
Author-email: mboszko@mac.com
License: MIT
Keywords: api,movie,film,movie database,movie review,watchlist,letterboxd,moviedb
Platform: UNKNOWN
Classifier: Development Status :: 3 - Alpha
Classifier: Intended Audience :: Developers
Classifier: License :: OSI Approved :: MIT License
Classifier: Operating System :: OS Independent
Classifier: Programming Language :: Python :: 3.6
Classifier: Programming Language :: Python :: 3.7
Classifier: Topic :: Internet :: WWW/HTTP :: Dynamic Content
Classifier: Topic :: Utilities
Requires-Python: >=3.6
